{
    "version": 1,
    "grid": {
        "width": 100,
        "height": 100
    },
    "wind": {
        "direction": 0,
        "strength": 0
    },
    "sensors": [
        {
            "x": 10,
            "y": 25,
            "pollution_value": 0.0,
            "polluted": true
        },
        {
            "x": 30,
            "y": 25,
            "pollution_value": 0.0,
            "polluted": true
        },
        {
            "x": 50,
            "y": 25,
            "pollution_value": 0.0,
            "polluted": true
        },
        {
            "x": 70,
            "y": 25,
            "pollution_value": 0.0,
            "polluted": true
        },
        {
            "x": 90,
            "y": 25,
            "pollution_value": 0.0,
            "polluted": true
        },
        {
            "x": 10,
            "y": 75,
            "pollution_value": 0.0,
            "polluted": true
        },
        {
            "x": 30,
            "y": 75,
            "pollution_value": 0.0,
            "polluted": true
        },
        {
            "x": 50,
            "y": 75,
            "pollution_value": 0.0,
            "polluted": true
        },
        {
            "x": 70,
            "y": 75,
            "pollution_value": 0.0,
            "polluted": true
        },
        {
            "x": 90,
            "y": 75,
            "pollution_value": 0.0,
            "polluted": true
        }
    ]
}